{
  "id": "base4-61",
  "set": "base4",
  "number": "61",
  "rarity": "Uncommon",
  "name": "Seel",
  "owner": null,
  "variant": null,
  "stage": "Basic",
  "hp": 60,
  "type": "Water",
  "types": [
    "Water"
  ],
  "pokedex": 86,
  "level": "12",
  "evolvesFromName": null,
  "evolvesFromDex": null,
  "species": {
    "en": "Sea Lion Pokémon"
  },
  "flavor": {
    "en": "The protruding horn on its head is very hard. This horn is used for bashing through thick ice."
  },
  "weight": "198 lbs",
  "height": "3'07\"",
  "illustrator": "Ken Sugimori",
  "weaknesses": [
    {
      "type": "Lightning",
      "value": "×2"
    }
  ],
  "resistances": [],
  "retreatCost": 1,
  "babyInfo": null,
  "attacks": [
    {
      "name": {
        "en": "Headbutt"
      },
      "cost": [
        "Water"
      ],
      "raw": "10",
      "value": 10,
      "modifier": null,
      "text": {
        "en": null
      }
    }
  ],
  "powers": [],
  "_lang": [
    "en"
  ]
}
