{
  "id": "gym1-22",
  "set": "gym1",
  "number": "22",
  "rarity": "Rare",
  "name": "Brock's Rhyhorn",
  "owner": "Brock",
  "variant": null,
  "stage": "Basic",
  "hp": 60,
  "type": "Fighting",
  "types": [
    "Fighting"
  ],
  "pokedex": 111,
  "level": "25",
  "evolvesFromName": null,
  "evolvesFromDex": null,
  "species": {
    "en": "Spikes Pokémon"
  },
  "flavor": {
    "en": null
  },
  "weight": "254 lbs",
  "height": "3'03\"",
  "illustrator": "Ken Sugimori",
  "weaknesses": [
    {
      "type": "Grass",
      "value": "×2"
    }
  ],
  "resistances": [
    {
      "type": "Lightning",
      "value": "-30"
    }
  ],
  "retreatCost": 2,
  "babyInfo": null,
  "attacks": [
    {
      "name": {
        "en": "Horn Toss"
      },
      "cost": [
        "Colorless",
        "Colorless"
      ],
      "raw": "20",
      "value": 20,
      "modifier": null,
      "text": {
        "en": "If your opponent has any Benched Pokémon, he or she chooses 1 of them and switches it with the Defending Pokémon. (Do the damage before switching the Pokémon.)"
      }
    },
    {
      "name": {
        "en": "Take Down"
      },
      "cost": [
        "Fighting",
        "Fighting",
        "Colorless"
      ],
      "raw": "40",
      "value": 40,
      "modifier": null,
      "text": {
        "en": "Brock's Rhyhorn does 10 damage to itself."
      }
    }
  ],
  "powers": [],
  "_lang": [
    "en"
  ]
}
